unreasonable_llama/__init__.py
unreasonable_llama/py.typed
unreasonable_llama-0.4.1.dist-info/LICENSE
unreasonable_llama-0.4.1.dist-info/METADATA
unreasonable_llama-0.4.1.dist-info/WHEEL
unreasonable_llama-0.4.1.dist-info/RECORD
