Metadata-Version: 2.1
Name: unreasonable-llama
Version: 0.4.1
Summary: HTTP API bindings for llama.cpp built-in example server
Home-page: https://github.com/SteelPh0enix/unreasonable-llama/
License: MIT
Keywords: llama.cpp,llama,llm,api,bindings,stateless
Author: SteelPh0enix
Author-email: wojciech_olech@hotmail.com
Requires-Python: >=3.12,<4.0
Classifier: License :: OSI Approved :: MIT License
Classifier: Programming Language :: Python :: 3
Classifier: Programming Language :: Python :: 3.12
Requires-Dist: httpx (>=0.27.2,<0.28.0)
Project-URL: Repository, https://github.com/SteelPh0enix/unreasonable-llama/
